components/__init__.py
components/component.py
components/floating.py
components/heading.py
components/horizontal_line.py
components/icon_text.py
components/text.py
components/text_line.py
core/__init__.py
core/engine.py
core/fonts_manager.py
core/handlers.py
core/layout.py
core/section.py
core/stylesheet.py
core/utils.py
preprocess/__init__.py
preprocess/preprocess.py
suli/__init__.py
suli/stylesheet.py
suli/components/__init__.py
suli/components/component.py
suli/components/floating.py
suli/components/heading.py
suli/components/horizontal_line.py
suli/components/icon_text.py
suli/components/text.py
suli/components/text_line.py
suli/core/__init__.py
suli/core/engine.py
suli/core/fonts_manager.py
suli/core/handlers.py
suli/core/layout.py
suli/core/section.py
suli/core/stylesheet.py
suli/core/utils.py
suli/preprocess/__init__.py
suli/preprocess/preprocess.py
suli-0.1.3.dist-info/METADATA
suli-0.1.3.dist-info/RECORD
suli-0.1.3.dist-info/WHEEL
suli-0.1.3.dist-info/top_level.txt
