Metadata-Version: 2.1
Name: suli
Version: 0.1.3
Summary: A template renderer
Home-page: https://bitbucket.org/trazolabs/suli
Author: Marcelo Jara
Author-email: marcelo@trazolabs.com
License: UNKNOWN
Platform: UNKNOWN
Classifier: Programming Language :: Python :: 3
Classifier: Operating System :: OS Independent
Requires-Dist: reportlab
Requires-Dist: wand
Requires-Dist: jinja2
